blik/__init__.py
blik/_version.py
blik/napari.yaml
blik/reader.py
blik/remote_data.py
blik/utils.py
blik/writer.py
blik/widgets/__init__.py
blik/widgets/file_reader.py
blik/widgets/filter.py
blik/widgets/main_widget.py
blik/widgets/picking.py
blik/widgets/power_spectrum.py
blik-0.9.2.dist-info/METADATA
blik-0.9.2.dist-info/WHEEL
blik-0.9.2.dist-info/entry_points.txt
blik-0.9.2.dist-info/licenses/LICENSE
blik-0.9.2.dist-info/RECORD
