Metadata-Version: 2.4
Name: blik
Version: 0.9.2
Summary: Python tool for visualising and interacting with cryo-ET and subtomogram averaging data.
Project-URL: homepage, https://github.com/brisvag/blik
Project-URL: repository, https://github.com/brisvag/blik
Author-email: Lorenzo Gaifas <brisvag@gmail.com>
License: GPLv3
License-File: LICENSE
Classifier: Development Status :: 3 - Alpha
Classifier: Framework :: napari
Classifier: License :: OSI Approved :: GNU General Public License v3 (GPLv3)
Classifier: Natural Language :: English
Classifier: Programming Language :: Python :: 3
Classifier: Programming Language :: Python :: 3.9
Classifier: Programming Language :: Python :: 3.10
Classifier: Programming Language :: Python :: 3.11
Classifier: Topic :: Scientific/Engineering :: Visualization
Classifier: Typing :: Typed
Requires-Python: >=3.10
Requires-Dist: cryohub>=0.6.4
Requires-Dist: cryotypes>=0.2.0
Requires-Dist: dask
Requires-Dist: einops
Requires-Dist: magicgui>=0.4.0
Requires-Dist: morphosamplers[segment]>=0.0.10
Requires-Dist: numpy
Requires-Dist: packaging
Requires-Dist: pandas
Requires-Dist: pydantic
Requires-Dist: scipy
Provides-Extra: all
Requires-Dist: napari-label-interpolator>=0.1.1; extra == 'all'
Requires-Dist: napari-properties-plotter; extra == 'all'
Requires-Dist: napari-properties-viewer; extra == 'all'
Requires-Dist: napari[all]>=0.6.0; extra == 'all'
Provides-Extra: dev
Requires-Dist: black; extra == 'dev'
Requires-Dist: ipython; extra == 'dev'
Requires-Dist: mypy; extra == 'dev'
Requires-Dist: napari[all]>=0.6.0; extra == 'dev'
Requires-Dist: pdbpp; extra == 'dev'
Requires-Dist: pre-commit; extra == 'dev'
Requires-Dist: pytest-cov; extra == 'dev'
Requires-Dist: pytest-qt; extra == 'dev'
Requires-Dist: pytest>=6.0; extra == 'dev'
Requires-Dist: rich; extra == 'dev'
Requires-Dist: ruff; extra == 'dev'
Provides-Extra: test
Requires-Dist: napari[all]>=0.6.0; extra == 'test'
Requires-Dist: pytest-cov; extra == 'test'
Requires-Dist: pytest-qt; extra == 'test'
Requires-Dist: pytest>=6.0; extra == 'test'
